otel_bootstrap/__init__.py
otel_bootstrap/_state.py
otel_bootstrap/config.py
otel_bootstrap/fastapi.py
otel_bootstrap/grpc.py
otel_bootstrap/http.py
otel_bootstrap/logging.py
otel_bootstrap/minio.py
otel_bootstrap/postgres.py
otel_bootstrap/redis.py
otel_bootstrap/tracer.py
otel_bootstrap-0.1.9.dist-info/METADATA
otel_bootstrap-0.1.9.dist-info/WHEEL
otel_bootstrap-0.1.9.dist-info/top_level.txt
otel_bootstrap-0.1.9.dist-info/RECORD
