Metadata-Version: 2.4
Name: otel-bootstrap
Version: 0.1.9
Summary: Simple OpenTelemetry bootstrap for FastAPI, SQLAlchemy, Redis (sync & async)
Author-email: Your Name <you@email.com>
License: MIT
Requires-Python: >=3.9
Requires-Dist: pydantic>=1.10
Requires-Dist: pydantic-settings>=2.0; python_version >= "3.9"
Requires-Dist: opentelemetry-sdk>=1.22
Requires-Dist: opentelemetry-exporter-otlp>=1.22
Requires-Dist: opentelemetry-instrumentation-fastapi
Requires-Dist: opentelemetry-instrumentation-grpc
Requires-Dist: opentelemetry-instrumentation-requests
Requires-Dist: opentelemetry-instrumentation-httpx
Requires-Dist: opentelemetry-instrumentation-sqlalchemy
Requires-Dist: opentelemetry-instrumentation-redis
